[
  {
    "main": "name",
    "question": "What's your name",
    "answer": "Or",
    "options": [
      "null"
    ]
  },
  {
    "main": "age",
    "question": "How old are you",
    "answer": "17",
    "options": [
      "15",
      "16",
      "17",
      "18",
      "19",
      "20"
    ]
  },
  {
    "main": "timeOfDay",
    "question": "At what times of the day\nDo you prefer to work at?",
    "answer": "Afternoon",
    "options": [
      "Morning",
      "Afternoon",
      "Evening"
    ]
  },
  {
    "main": "prefarableHoursToWork",
    "question": "How much time would you \nlike to work every day",
    "answer": "5 hours",
    "options": [
      "2 hours",
      "3 hours",
      "4 hours",
      "5 hours",
      "6 hours",
      "7 hours",
      "I dont care, just help me finish all of my work"
    ]
  },
  {
    "main": "weekends",
    "question": "Can you work in the weekends?",
    "answer": "yes",
    "options": [
      "yes",
      "no"
    ]
  },
  {
    "main": "wayOfWork",
    "question": "Do you prefer to work on each task\na couple of hours in a\nrow or in different times",
    "answer": "different times",
    "options": [
      "in a row",
      "different times"
    ]
  }
]